{
    "Version": "1.2",
    "Data": {
        "Source": "e:\\fpsgame\\fpsgame\\intermediate\\build\\win64\\x64\\unrealeditor\\development\\fpsgame\\module.fpsgame.cpp",
        "ProvidedModule": "",
        "PCH": "e:\\fpsgame\\fpsgame\\intermediate\\build\\win64\\x64\\fpsgameeditor\\development\\unrealed\\sharedpch.unrealed.project.valapi.valexpapi.cpp20.h.pch",
        "Includes": [
            "e:\\fpsgame\\fpsgame\\intermediate\\build\\win64\\x64\\unrealeditor\\development\\fpsgame\\definitions.fpsgame.h",
            "e:\\fpsgame\\fpsgame\\intermediate\\build\\win64\\unrealeditor\\inc\\fpsgame\\uht\\envquerycontext_target.gen.cpp",
            "e:\\fpsgame\\fpsgame\\source\\fpsgame\\variant_shooter\\ai\\envquerycontext_target.h",
            "k:\\ue_5.6\\engine\\source\\runtime\\aimodule\\classes\\environmentquery\\envquerycontext.h",
            "k:\\ue_5.6\\engine\\intermediate\\build\\win64\\unrealeditor\\inc\\aimodule\\uht\\envquerycontext.generated.h",
            "e:\\fpsgame\\fpsgame\\intermediate\\build\\win64\\unrealeditor\\inc\\fpsgame\\uht\\envquerycontext_target.generated.h",
            "e:\\fpsgame\\fpsgame\\intermediate\\build\\win64\\unrealeditor\\inc\\fpsgame\\uht\\fpsgamecameramanager.gen.cpp",
            "e:\\fpsgame\\fpsgame\\source\\fpsgame\\fpsgamecameramanager.h",
            "e:\\fpsgame\\fpsgame\\intermediate\\build\\win64\\unrealeditor\\inc\\fpsgame\\uht\\fpsgamecameramanager.generated.h",
            "e:\\fpsgame\\fpsgame\\intermediate\\build\\win64\\unrealeditor\\inc\\fpsgame\\uht\\fpsgamegamemode.gen.cpp",
            "e:\\fpsgame\\fpsgame\\source\\fpsgame\\fpsgamegamemode.h",
            "k:\\ue_5.6\\engine\\source\\runtime\\engine\\classes\\gameframework\\gamemodebase.h",
            "k:\\ue_5.6\\engine\\source\\runtime\\engine\\classes\\engine\\serverstatreplicator.h",
            "k:\\ue_5.6\\engine\\intermediate\\build\\win64\\unrealeditor\\inc\\engine\\uht\\serverstatreplicator.generated.h",
            "k:\\ue_5.6\\engine\\intermediate\\build\\win64\\unrealeditor\\inc\\engine\\uht\\gamemodebase.generated.h",
            "e:\\fpsgame\\fpsgame\\intermediate\\build\\win64\\unrealeditor\\inc\\fpsgame\\uht\\fpsgamegamemode.generated.h",
            "e:\\fpsgame\\fpsgame\\intermediate\\build\\win64\\unrealeditor\\inc\\fpsgame\\uht\\fpsgameplayercontroller.gen.cpp",
            "e:\\fpsgame\\fpsgame\\source\\fpsgame\\fpsgameplayercontroller.h",
            "e:\\fpsgame\\fpsgame\\intermediate\\build\\win64\\unrealeditor\\inc\\fpsgame\\uht\\fpsgameplayercontroller.generated.h",
            "e:\\fpsgame\\fpsgame\\intermediate\\build\\win64\\unrealeditor\\inc\\fpsgame\\uht\\horrorgamemode.gen.cpp",
            "e:\\fpsgame\\fpsgame\\source\\fpsgame\\variant_horror\\horrorgamemode.h",
            "e:\\fpsgame\\fpsgame\\intermediate\\build\\win64\\unrealeditor\\inc\\fpsgame\\uht\\horrorgamemode.generated.h",
            "e:\\fpsgame\\fpsgame\\intermediate\\build\\win64\\unrealeditor\\inc\\fpsgame\\uht\\horrorplayercontroller.gen.cpp",
            "e:\\fpsgame\\fpsgame\\source\\fpsgame\\variant_horror\\horrorplayercontroller.h",
            "e:\\fpsgame\\fpsgame\\intermediate\\build\\win64\\unrealeditor\\inc\\fpsgame\\uht\\horrorplayercontroller.generated.h",
            "e:\\fpsgame\\fpsgame\\intermediate\\build\\win64\\unrealeditor\\inc\\fpsgame\\uht\\horrorui.gen.cpp",
            "e:\\fpsgame\\fpsgame\\source\\fpsgame\\variant_horror\\horrorui.h",
            "k:\\ue_5.6\\engine\\source\\runtime\\umg\\public\\blueprint\\userwidget.h",
            "k:\\ue_5.6\\engine\\source\\runtime\\umg\\public\\blueprint\\umgsequenceplaymode.h",
            "k:\\ue_5.6\\engine\\intermediate\\build\\win64\\unrealeditor\\inc\\umg\\uht\\umgsequenceplaymode.generated.h",
            "k:\\ue_5.6\\engine\\source\\runtime\\umg\\public\\blueprint\\widgetchild.h",
            "k:\\ue_5.6\\engine\\intermediate\\build\\win64\\unrealeditor\\inc\\umg\\uht\\widgetchild.generated.h",
            "k:\\ue_5.6\\engine\\source\\runtime\\coreuobject\\public\\uobject\\objectsavecontext.h",
            "k:\\ue_5.6\\engine\\source\\runtime\\coreuobject\\public\\uobject\\cookenums.h",
            "k:\\ue_5.6\\engine\\source\\runtime\\coreuobject\\public\\uobject\\objectsaveoverride.h",
            "k:\\ue_5.6\\engine\\source\\runtime\\coreuobject\\public\\cooker\\cookdependency.h",
            "k:\\ue_5.6\\engine\\source\\runtime\\umg\\public\\components\\slatewrappertypes.h",
            "k:\\ue_5.6\\engine\\intermediate\\build\\win64\\unrealeditor\\inc\\umg\\uht\\slatewrappertypes.generated.h",
            "k:\\ue_5.6\\engine\\source\\runtime\\umg\\public\\components\\widget.h",
            "k:\\ue_5.6\\engine\\source\\runtime\\umg\\public\\binding\\states\\widgetstatebitfield.h",
            "k:\\ue_5.6\\engine\\intermediate\\build\\win64\\unrealeditor\\inc\\umg\\uht\\widgetstatebitfield.generated.h",
            "k:\\ue_5.6\\engine\\source\\runtime\\fieldnotification\\public\\fieldnotificationdeclaration.h",
            "k:\\ue_5.6\\engine\\source\\runtime\\fieldnotification\\public\\ifieldnotificationclassdescriptor.h",
            "k:\\ue_5.6\\engine\\source\\runtime\\fieldnotification\\public\\inotifyfieldvaluechanged.h",
            "k:\\ue_5.6\\engine\\intermediate\\build\\win64\\unrealeditor\\inc\\fieldnotification\\uht\\inotifyfieldvaluechanged.generated.h",
            "k:\\ue_5.6\\engine\\source\\runtime\\umg\\public\\components\\visual.h",
            "k:\\ue_5.6\\engine\\intermediate\\build\\win64\\unrealeditor\\inc\\umg\\uht\\visual.generated.h",
            "k:\\ue_5.6\\engine\\source\\runtime\\umg\\public\\slate\\widgettransform.h",
            "k:\\ue_5.6\\engine\\intermediate\\build\\win64\\unrealeditor\\inc\\umg\\uht\\widgettransform.generated.h",
            "k:\\ue_5.6\\engine\\source\\runtime\\umg\\public\\blueprint\\widgetnavigation.h",
            "k:\\ue_5.6\\engine\\source\\runtime\\slatecore\\public\\types\\navigationmetadata.h",
            "k:\\ue_5.6\\engine\\intermediate\\build\\win64\\unrealeditor\\inc\\umg\\uht\\widgetnavigation.generated.h",
            "k:\\ue_5.6\\engine\\intermediate\\build\\win64\\unrealeditor\\inc\\umg\\uht\\widget.generated.h",
            "k:\\ue_5.6\\engine\\source\\runtime\\umg\\public\\components\\namedslotinterface.h",
            "k:\\ue_5.6\\engine\\intermediate\\build\\win64\\unrealeditor\\inc\\umg\\uht\\namedslotinterface.generated.h",
            "k:\\ue_5.6\\engine\\source\\runtime\\slate\\public\\widgets\\layout\\anchors.h",
            "k:\\ue_5.6\\engine\\intermediate\\build\\win64\\unrealeditor\\inc\\slate\\uht\\anchors.generated.h",
            "k:\\ue_5.6\\engine\\source\\runtime\\umg\\public\\animation\\widgetanimationevents.h",
            "k:\\ue_5.6\\engine\\intermediate\\build\\win64\\unrealeditor\\inc\\umg\\uht\\widgetanimationevents.generated.h",
            "k:\\ue_5.6\\engine\\source\\runtime\\umg\\public\\animation\\widgetanimationhandle.h",
            "k:\\ue_5.6\\engine\\intermediate\\build\\win64\\unrealeditor\\inc\\umg\\uht\\widgetanimationhandle.generated.h",
            "k:\\ue_5.6\\engine\\source\\runtime\\umg\\public\\animation\\widgetanimationstate.h",
            "k:\\ue_5.6\\engine\\source\\runtime\\umg\\public\\animation\\umgsequencetickmanager.h",
            "k:\\ue_5.6\\engine\\source\\runtime\\moviescene\\public\\moviescenelatentactionmanager.h",
            "k:\\ue_5.6\\engine\\intermediate\\build\\win64\\unrealeditor\\inc\\umg\\uht\\umgsequencetickmanager.generated.h",
            "k:\\ue_5.6\\engine\\source\\runtime\\moviescene\\public\\evaluation\\moviesceneplayback.h",
            "k:\\ue_5.6\\engine\\source\\runtime\\moviescene\\public\\evaluation\\moviescenesequencetransform.h",
            "k:\\ue_5.6\\engine\\source\\runtime\\moviescene\\public\\moviescenefwd.h",
            "k:\\ue_5.6\\engine\\intermediate\\build\\win64\\unrealeditor\\inc\\moviescene\\uht\\moviescenefwd.generated.h",
            "k:\\ue_5.6\\engine\\source\\runtime\\moviescene\\public\\evaluation\\moviescenetimetransform.h",
            "k:\\ue_5.6\\engine\\intermediate\\build\\win64\\unrealeditor\\inc\\moviescene\\uht\\moviescenetimetransform.generated.h",
            "k:\\ue_5.6\\engine\\source\\runtime\\moviescene\\public\\evaluation\\moviescenetimewarping.h",
            "k:\\ue_5.6\\engine\\intermediate\\build\\win64\\unrealeditor\\inc\\moviescene\\uht\\moviescenetimewarping.generated.h",
            "k:\\ue_5.6\\engine\\source\\runtime\\moviescene\\public\\variants\\moviescenetimewarpvariant.h",
            "k:\\ue_5.6\\engine\\source\\runtime\\moviescene\\public\\variants\\moviescenenumericvariant.h",
            "k:\\ue_5.6\\engine\\intermediate\\build\\win64\\unrealeditor\\inc\\moviescene\\uht\\moviescenenumericvariant.generated.h",
            "k:\\ue_5.6\\engine\\intermediate\\build\\win64\\unrealeditor\\inc\\moviescene\\uht\\moviescenetimewarpvariant.generated.h",
            "k:\\ue_5.6\\engine\\intermediate\\build\\win64\\unrealeditor\\inc\\moviescene\\uht\\moviescenesequencetransform.generated.h",
            "k:\\ue_5.6\\engine\\source\\runtime\\moviescene\\public\\moviescenetimehelpers.h",
            "k:\\ue_5.6\\engine\\source\\runtime\\moviescene\\public\\evaluation\\moviesceneplaybackmanager.h",
            "k:\\ue_5.6\\engine\\source\\runtime\\moviescene\\public\\entitysystem\\moviescenesharedplaybackstate.h",
            "k:\\ue_5.6\\engine\\source\\runtime\\moviescene\\public\\compilation\\moviescenecompileddataid.h",
            "k:\\ue_5.6\\engine\\source\\runtime\\moviescene\\public\\entitysystem\\moviescenesequenceinstancehandle.h",
            "k:\\ue_5.6\\engine\\source\\runtime\\moviescene\\public\\entitysystem\\moviescenecomponentdebug.h",
            "k:\\ue_5.6\\engine\\source\\runtime\\moviescene\\public\\entitysystem\\moviesceneentitysystemtypes.h",
            "k:\\ue_5.6\\engine\\source\\runtime\\moviescene\\public\\entitysystem\\moviesceneentityids.h",
            "k:\\ue_5.6\\engine\\source\\runtime\\core\\public\\misc\\inlinevalue.h",
            "k:\\ue_5.6\\engine\\source\\runtime\\moviescene\\public\\evaluation\\moviesceneevaluationoperand.h",
            "k:\\ue_5.6\\engine\\source\\runtime\\moviescene\\public\\moviescenesequenceid.h",
            "k:\\ue_5.6\\engine\\intermediate\\build\\win64\\unrealeditor\\inc\\moviescene\\uht\\moviescenesequenceid.generated.h",
            "k:\\ue_5.6\\engine\\intermediate\\build\\win64\\unrealeditor\\inc\\moviescene\\uht\\moviesceneevaluationoperand.generated.h",
            "k:\\ue_5.6\\engine\\source\\runtime\\moviescene\\public\\evaluation\\moviesceneplaybackcapabilities.h",
            "k:\\ue_5.6\\engine\\source\\runtime\\moviescene\\public\\evaluation\\imoviesceneplaybackcapability.h",
            "k:\\ue_5.6\\engine\\source\\runtime\\moviescene\\public\\entitysystem\\relativeptr.h",
            "k:\\ue_5.6\\engine\\source\\runtime\\moviescene\\public\\evaluation\\moviescenepreanimatedstate.h",
            "k:\\ue_5.6\\engine\\intermediate\\build\\win64\\unrealeditor\\inc\\umg\\uht\\userwidget.generated.h",
            "e:\\fpsgame\\fpsgame\\intermediate\\build\\win64\\unrealeditor\\inc\\fpsgame\\uht\\horrorui.generated.h",
            "e:\\fpsgame\\fpsgame\\intermediate\\build\\win64\\unrealeditor\\inc\\fpsgame\\uht\\shooteraicontroller.gen.cpp",
            "e:\\fpsgame\\fpsgame\\source\\fpsgame\\variant_shooter\\ai\\shooteraicontroller.h",
            "k:\\ue_5.6\\engine\\source\\runtime\\aimodule\\classes\\aicontroller.h",
            "k:\\ue_5.6\\engine\\source\\runtime\\aimodule\\classes\\aitypes.h",
            "k:\\ue_5.6\\engine\\source\\runtime\\navigationsystem\\public\\navigationsystemtypes.h",
            "k:\\ue_5.6\\engine\\source\\runtime\\engine\\classes\\ai\\navigation\\navagentselector.h",
            "k:\\ue_5.6\\engine\\intermediate\\build\\win64\\unrealeditor\\inc\\engine\\uht\\navagentselector.generated.h",
            "k:\\ue_5.6\\engine\\intermediate\\build\\win64\\unrealeditor\\inc\\aimodule\\uht\\aitypes.generated.h",
            "k:\\ue_5.6\\engine\\source\\runtime\\aimodule\\classes\\perception\\aiperceptionlistenerinterface.h",
            "k:\\ue_5.6\\engine\\intermediate\\build\\win64\\unrealeditor\\inc\\aimodule\\uht\\aiperceptionlistenerinterface.generated.h",
            "k:\\ue_5.6\\engine\\source\\runtime\\aimodule\\classes\\genericteamagentinterface.h",
            "k:\\ue_5.6\\engine\\intermediate\\build\\win64\\unrealeditor\\inc\\aimodule\\uht\\genericteamagentinterface.generated.h",
            "k:\\ue_5.6\\engine\\source\\runtime\\engine\\public\\visuallogger\\visualloggerdebugsnapshotinterface.h",
            "k:\\ue_5.6\\engine\\intermediate\\build\\win64\\unrealeditor\\inc\\engine\\uht\\visualloggerdebugsnapshotinterface.generated.h",
            "k:\\ue_5.6\\engine\\intermediate\\build\\win64\\unrealeditor\\inc\\aimodule\\uht\\aicontroller.generated.h",
            "e:\\fpsgame\\fpsgame\\intermediate\\build\\win64\\unrealeditor\\inc\\fpsgame\\uht\\shooteraicontroller.generated.h",
            "k:\\ue_5.6\\engine\\source\\runtime\\aimodule\\classes\\perception\\aiperceptiontypes.h",
            "k:\\ue_5.6\\engine\\intermediate\\build\\win64\\unrealeditor\\inc\\aimodule\\uht\\aiperceptiontypes.generated.h",
            "e:\\fpsgame\\fpsgame\\intermediate\\build\\win64\\unrealeditor\\inc\\fpsgame\\uht\\shooterbulletcounterui.gen.cpp",
            "e:\\fpsgame\\fpsgame\\source\\fpsgame\\variant_shooter\\shooterbulletcounterui.h",
            "e:\\fpsgame\\fpsgame\\intermediate\\build\\win64\\unrealeditor\\inc\\fpsgame\\uht\\shooterbulletcounterui.generated.h",
            "e:\\fpsgame\\fpsgame\\intermediate\\build\\win64\\unrealeditor\\inc\\fpsgame\\uht\\shootergamemode.gen.cpp",
            "e:\\fpsgame\\fpsgame\\source\\fpsgame\\variant_shooter\\shootergamemode.h",
            "e:\\fpsgame\\fpsgame\\intermediate\\build\\win64\\unrealeditor\\inc\\fpsgame\\uht\\shootergamemode.generated.h",
            "e:\\fpsgame\\fpsgame\\intermediate\\build\\win64\\unrealeditor\\inc\\fpsgame\\uht\\shooterpickup.gen.cpp",
            "e:\\fpsgame\\fpsgame\\source\\fpsgame\\variant_shooter\\shooterpickup.h",
            "e:\\fpsgame\\fpsgame\\intermediate\\build\\win64\\unrealeditor\\inc\\fpsgame\\uht\\shooterpickup.generated.h",
            "e:\\fpsgame\\fpsgame\\intermediate\\build\\win64\\unrealeditor\\inc\\fpsgame\\uht\\shooterplayercontroller.gen.cpp",
            "e:\\fpsgame\\fpsgame\\source\\fpsgame\\variant_shooter\\shooterplayercontroller.h",
            "e:\\fpsgame\\fpsgame\\intermediate\\build\\win64\\unrealeditor\\inc\\fpsgame\\uht\\shooterplayercontroller.generated.h",
            "e:\\fpsgame\\fpsgame\\intermediate\\build\\win64\\unrealeditor\\inc\\fpsgame\\uht\\shooterprojectile.gen.cpp",
            "e:\\fpsgame\\fpsgame\\source\\fpsgame\\variant_shooter\\shooterprojectile.h",
            "e:\\fpsgame\\fpsgame\\intermediate\\build\\win64\\unrealeditor\\inc\\fpsgame\\uht\\shooterprojectile.generated.h",
            "e:\\fpsgame\\fpsgame\\intermediate\\build\\win64\\unrealeditor\\inc\\fpsgame\\uht\\shooterstatetreeutility.gen.cpp",
            "e:\\fpsgame\\fpsgame\\source\\fpsgame\\variant_shooter\\ai\\shooterstatetreeutility.h",
            "k:\\ue_5.6\\engine\\plugins\\runtime\\statetree\\source\\statetreemodule\\public\\statetreetaskbase.h",
            "k:\\ue_5.6\\engine\\plugins\\runtime\\statetree\\source\\statetreemodule\\public\\statetreenodebase.h",
            "k:\\ue_5.6\\engine\\plugins\\runtime\\statetree\\source\\statetreemodule\\public\\statetreetypes.h",
            "k:\\ue_5.6\\engine\\plugins\\runtime\\propertybindingutils\\source\\propertybindingutils\\public\\propertybindingdataview.h",
            "k:\\ue_5.6\\engine\\source\\runtime\\coreuobject\\public\\structutils\\structview.h",
            "k:\\ue_5.6\\engine\\source\\runtime\\coreuobject\\public\\structutils\\instancedstruct.h",
            "k:\\ue_5.6\\engine\\source\\runtime\\coreuobject\\public\\structutils\\structutils.h",
            "k:\\ue_5.6\\engine\\intermediate\\build\\win64\\unrealeditor\\inc\\coreuobject\\uht\\instancedstruct.generated.h",
            "k:\\ue_5.6\\engine\\source\\runtime\\coreuobject\\public\\structutils\\sharedstruct.h",
            "k:\\ue_5.6\\engine\\source\\runtime\\coreuobject\\public\\structutils\\structutilstypes.h",
            "k:\\ue_5.6\\engine\\intermediate\\build\\win64\\unrealeditor\\inc\\coreuobject\\uht\\sharedstruct.generated.h",
            "k:\\ue_5.6\\engine\\source\\runtime\\coreuobject\\public\\structutils\\propertybag.h",
            "k:\\ue_5.6\\engine\\intermediate\\build\\win64\\unrealeditor\\inc\\coreuobject\\uht\\propertybag.generated.h",
            "k:\\ue_5.6\\engine\\source\\runtime\\gameplaytags\\classes\\gameplaytagcontainer.h",
            "k:\\ue_5.6\\engine\\source\\runtime\\core\\public\\misc\\comparisonutility.h",
            "k:\\ue_5.6\\engine\\intermediate\\build\\win64\\unrealeditor\\inc\\gameplaytags\\uht\\gameplaytagcontainer.generated.h",
            "k:\\ue_5.6\\engine\\plugins\\runtime\\statetree\\source\\statetreemodule\\public\\statetreedelegate.h",
            "k:\\ue_5.6\\engine\\plugins\\runtime\\statetree\\source\\statetreemodule\\public\\statetreeindextypes.h",
            "k:\\ue_5.6\\engine\\plugins\\runtime\\propertybindingutils\\source\\propertybindingutils\\public\\propertybindingtypes.h",
            "k:\\ue_5.6\\engine\\plugins\\runtime\\propertybindingutils\\intermediate\\build\\win64\\unrealeditor\\inc\\propertybindingutils\\uht\\propertybindingtypes.generated.h",
            "k:\\ue_5.6\\engine\\plugins\\runtime\\statetree\\intermediate\\build\\win64\\unrealeditor\\inc\\statetreemodule\\uht\\statetreeindextypes.generated.h",
            "k:\\ue_5.6\\engine\\plugins\\runtime\\statetree\\intermediate\\build\\win64\\unrealeditor\\inc\\statetreemodule\\uht\\statetreedelegate.generated.h",
            "k:\\ue_5.6\\engine\\plugins\\runtime\\statetree\\source\\statetreemodule\\public\\statetreetasksstatus.h",
            "k:\\ue_5.6\\engine\\plugins\\runtime\\statetree\\intermediate\\build\\win64\\unrealeditor\\inc\\statetreemodule\\uht\\statetreetasksstatus.generated.h",
            "k:\\ue_5.6\\engine\\plugins\\runtime\\statetree\\intermediate\\build\\win64\\unrealeditor\\inc\\statetreemodule\\uht\\statetreetypes.generated.h",
            "k:\\ue_5.6\\engine\\plugins\\runtime\\statetree\\intermediate\\build\\win64\\unrealeditor\\inc\\statetreemodule\\uht\\statetreenodebase.generated.h",
            "k:\\ue_5.6\\engine\\plugins\\runtime\\statetree\\source\\statetreemodule\\public\\statetreeexecutiontypes.h",
            "k:\\ue_5.6\\engine\\plugins\\runtime\\statetree\\source\\statetreemodule\\public\\statetreeevents.h",
            "k:\\ue_5.6\\engine\\plugins\\runtime\\statetree\\intermediate\\build\\win64\\unrealeditor\\inc\\statetreemodule\\uht\\statetreeevents.generated.h",
            "k:\\ue_5.6\\engine\\plugins\\runtime\\statetree\\source\\statetreemodule\\public\\statetreeexecutionextension.h",
            "k:\\ue_5.6\\engine\\plugins\\runtime\\statetree\\intermediate\\build\\win64\\unrealeditor\\inc\\statetreemodule\\uht\\statetreeexecutionextension.generated.h",
            "k:\\ue_5.6\\engine\\plugins\\runtime\\statetree\\source\\statetreemodule\\public\\statetreestatepath.h",
            "k:\\ue_5.6\\engine\\plugins\\runtime\\statetree\\intermediate\\build\\win64\\unrealeditor\\inc\\statetreemodule\\uht\\statetreeexecutiontypes.generated.h",
            "k:\\ue_5.6\\engine\\plugins\\runtime\\statetree\\intermediate\\build\\win64\\unrealeditor\\inc\\statetreemodule\\uht\\statetreetaskbase.generated.h",
            "k:\\ue_5.6\\engine\\plugins\\runtime\\statetree\\source\\statetreemodule\\public\\statetreeconditionbase.h",
            "k:\\ue_5.6\\engine\\plugins\\runtime\\statetree\\intermediate\\build\\win64\\unrealeditor\\inc\\statetreemodule\\uht\\statetreeconditionbase.generated.h",
            "e:\\fpsgame\\fpsgame\\intermediate\\build\\win64\\unrealeditor\\inc\\fpsgame\\uht\\shooterstatetreeutility.generated.h",
            "e:\\fpsgame\\fpsgame\\intermediate\\build\\win64\\unrealeditor\\inc\\fpsgame\\uht\\shooterui.gen.cpp",
            "e:\\fpsgame\\fpsgame\\source\\fpsgame\\variant_shooter\\shooterui.h",
            "e:\\fpsgame\\fpsgame\\intermediate\\build\\win64\\unrealeditor\\inc\\fpsgame\\uht\\shooterui.generated.h",
            "e:\\fpsgame\\fpsgame\\intermediate\\build\\win64\\unrealeditor\\inc\\fpsgame\\uht\\shooterweapon.gen.cpp",
            "e:\\fpsgame\\fpsgame\\source\\fpsgame\\variant_shooter\\shooterweapon.h",
            "e:\\fpsgame\\fpsgame\\source\\fpsgame\\variant_shooter\\shooterweaponholder.h",
            "e:\\fpsgame\\fpsgame\\intermediate\\build\\win64\\unrealeditor\\inc\\fpsgame\\uht\\shooterweaponholder.generated.h",
            "e:\\fpsgame\\fpsgame\\intermediate\\build\\win64\\unrealeditor\\inc\\fpsgame\\uht\\shooterweapon.generated.h",
            "e:\\fpsgame\\fpsgame\\intermediate\\build\\win64\\unrealeditor\\inc\\fpsgame\\uht\\shooterweaponholder.gen.cpp",
            "e:\\fpsgame\\fpsgame\\intermediate\\build\\win64\\x64\\unrealeditor\\development\\fpsgame\\permoduleinline.gen.cpp",
            "k:\\ue_5.6\\engine\\source\\runtime\\core\\public\\hal\\permoduleinline.inl",
            "e:\\fpsgame\\fpsgame\\source\\fpsgame\\fpsgame.cpp",
            "e:\\fpsgame\\fpsgame\\source\\fpsgame\\fpsgame.h",
            "e:\\fpsgame\\fpsgame\\source\\fpsgame\\fpsgamecameramanager.cpp",
            "e:\\fpsgame\\fpsgame\\source\\fpsgame\\fpsgamegamemode.cpp",
            "e:\\fpsgame\\fpsgame\\source\\fpsgame\\fpsgameplayercontroller.cpp",
            "k:\\ue_5.6\\engine\\plugins\\enhancedinput\\source\\enhancedinput\\public\\enhancedinputsubsystems.h",
            "k:\\ue_5.6\\engine\\plugins\\enhancedinput\\source\\enhancedinput\\public\\enhancedinputsubsysteminterface.h",
            "k:\\ue_5.6\\engine\\plugins\\enhancedinput\\source\\enhancedinput\\public\\enhancedplayerinput.h",
            "k:\\ue_5.6\\engine\\source\\runtime\\engine\\classes\\gameframework\\playerinput.h",
            "k:\\ue_5.6\\engine\\source\\runtime\\engine\\public\\gesturerecognizer.h",
            "k:\\ue_5.6\\engine\\source\\runtime\\engine\\public\\keystate.h",
            "k:\\ue_5.6\\engine\\intermediate\\build\\win64\\unrealeditor\\inc\\engine\\uht\\playerinput.generated.h",
            "k:\\ue_5.6\\engine\\plugins\\enhancedinput\\source\\enhancedinput\\public\\inputaction.h",
            "k:\\ue_5.6\\engine\\plugins\\enhancedinput\\source\\enhancedinput\\public\\inputmodifiers.h",
            "k:\\ue_5.6\\engine\\plugins\\enhancedinput\\source\\enhancedinput\\public\\inputactionvalue.h",
            "k:\\ue_5.6\\engine\\plugins\\enhancedinput\\intermediate\\build\\win64\\unrealeditor\\inc\\enhancedinput\\uht\\inputactionvalue.generated.h",
            "k:\\ue_5.6\\engine\\plugins\\enhancedinput\\intermediate\\build\\win64\\unrealeditor\\inc\\enhancedinput\\uht\\inputmodifiers.generated.h",
            "k:\\ue_5.6\\engine\\plugins\\enhancedinput\\source\\enhancedinput\\public\\inputtriggers.h",
            "k:\\ue_5.6\\engine\\plugins\\enhancedinput\\intermediate\\build\\win64\\unrealeditor\\inc\\enhancedinput\\uht\\inputtriggers.generated.h",
            "k:\\ue_5.6\\engine\\plugins\\enhancedinput\\intermediate\\build\\win64\\unrealeditor\\inc\\enhancedinput\\uht\\inputaction.generated.h",
            "k:\\ue_5.6\\engine\\source\\runtime\\gameplaytags\\public\\nativegameplaytags.h",
            "k:\\ue_5.6\\engine\\source\\runtime\\gameplaytags\\classes\\gameplaytagsmanager.h",
            "k:\\ue_5.6\\engine\\intermediate\\build\\win64\\unrealeditor\\inc\\gameplaytags\\uht\\gameplaytagsmanager.generated.h",
            "k:\\ue_5.6\\engine\\plugins\\enhancedinput\\intermediate\\build\\win64\\unrealeditor\\inc\\enhancedinput\\uht\\enhancedplayerinput.generated.h",
            "k:\\ue_5.6\\engine\\plugins\\enhancedinput\\intermediate\\build\\win64\\unrealeditor\\inc\\enhancedinput\\uht\\enhancedinputsubsysteminterface.generated.h",
            "k:\\ue_5.6\\engine\\plugins\\enhancedinput\\intermediate\\build\\win64\\unrealeditor\\inc\\enhancedinput\\uht\\enhancedinputsubsystems.generated.h",
            "k:\\ue_5.6\\engine\\plugins\\enhancedinput\\source\\enhancedinput\\public\\inputmappingcontext.h",
            "k:\\ue_5.6\\engine\\plugins\\enhancedinput\\source\\enhancedinput\\public\\enhancedactionkeymapping.h",
            "k:\\ue_5.6\\engine\\plugins\\enhancedinput\\intermediate\\build\\win64\\unrealeditor\\inc\\enhancedinput\\uht\\enhancedactionkeymapping.generated.h",
            "k:\\ue_5.6\\engine\\plugins\\enhancedinput\\intermediate\\build\\win64\\unrealeditor\\inc\\enhancedinput\\uht\\inputmappingcontext.generated.h",
            "e:\\fpsgame\\fpsgame\\source\\fpsgame\\variant_horror\\horrorcharacter.cpp",
            "e:\\fpsgame\\fpsgame\\source\\fpsgame\\variant_horror\\horrorcharacter.h",
            "e:\\fpsgame\\fpsgame\\source\\fpsgame\\fpsgamecharacter.h",
            "k:\\ue_5.6\\engine\\source\\runtime\\engine\\classes\\gameframework\\character.h",
            "k:\\ue_5.6\\engine\\source\\runtime\\engine\\classes\\gameframework\\charactermovementreplication.h",
            "k:\\ue_5.6\\engine\\source\\runtime\\net\\core\\public\\net\\core\\nettoken\\nettokenexportcontext.h",
            "k:\\ue_5.6\\engine\\source\\runtime\\experimental\\iris\\core\\public\\iris\\serialization\\irisobjectreferencepackagemap.h",
            "k:\\ue_5.6\\engine\\intermediate\\build\\win64\\unrealeditor\\inc\\iriscore\\uht\\irisobjectreferencepackagemap.generated.h",
            "k:\\ue_5.6\\engine\\intermediate\\build\\win64\\unrealeditor\\inc\\engine\\uht\\charactermovementreplication.generated.h",
            "k:\\ue_5.6\\engine\\source\\runtime\\engine\\classes\\gameframework\\rootmotionsource.h",
            "k:\\ue_5.6\\engine\\intermediate\\build\\win64\\unrealeditor\\inc\\engine\\uht\\rootmotionsource.generated.h",
            "k:\\ue_5.6\\engine\\intermediate\\build\\win64\\unrealeditor\\inc\\engine\\uht\\character.generated.h",
            "k:\\ue_5.6\\engine\\plugins\\online\\onlinesubsystem\\source\\public\\interfaces\\onlinesessioninterface.h",
            "k:\\ue_5.6\\engine\\plugins\\online\\onlinesubsystem\\source\\public\\onlinesubsystemtypes.h",
            "k:\\ue_5.6\\engine\\plugins\\online\\onlinesubsystem\\source\\public\\onlinesubsystemnames.h",
            "k:\\ue_5.6\\engine\\plugins\\online\\onlinesubsystem\\source\\public\\onlinedelegatemacros.h",
            "k:\\ue_5.6\\engine\\plugins\\online\\onlinesubsystem\\source\\public\\interfaces\\onlinesessiondelegates.h",
            "k:\\ue_5.6\\engine\\plugins\\online\\onlinesubsystem\\source\\public\\onlinekeyvaluepair.h",
            "e:\\fpsgame\\fpsgame\\intermediate\\build\\win64\\unrealeditor\\inc\\fpsgame\\uht\\fpsgamecharacter.generated.h",
            "e:\\fpsgame\\fpsgame\\intermediate\\build\\win64\\unrealeditor\\inc\\fpsgame\\uht\\horrorcharacter.generated.h",
            "k:\\ue_5.6\\engine\\source\\runtime\\engine\\classes\\gameframework\\charactermovementcomponent.h",
            "k:\\ue_5.6\\engine\\source\\runtime\\engine\\classes\\ai\\navigation\\navigationavoidancetypes.h",
            "k:\\ue_5.6\\engine\\intermediate\\build\\win64\\unrealeditor\\inc\\engine\\uht\\navigationavoidancetypes.generated.h",
            "k:\\ue_5.6\\engine\\source\\runtime\\engine\\public\\ai\\rvoavoidanceinterface.h",
            "k:\\ue_5.6\\engine\\intermediate\\build\\win64\\unrealeditor\\inc\\engine\\uht\\rvoavoidanceinterface.generated.h",
            "k:\\ue_5.6\\engine\\source\\runtime\\engine\\classes\\gameframework\\pawnmovementcomponent.h",
            "k:\\ue_5.6\\engine\\source\\runtime\\engine\\classes\\gameframework\\navmovementcomponent.h",
            "k:\\ue_5.6\\engine\\source\\runtime\\engine\\classes\\gameframework\\navmovementinterface.h",
            "k:\\ue_5.6\\engine\\intermediate\\build\\win64\\unrealeditor\\inc\\engine\\uht\\navmovementinterface.generated.h",
            "k:\\ue_5.6\\engine\\source\\runtime\\engine\\classes\\ai\\navigation\\pathfollowingagentinterface.h",
            "k:\\ue_5.6\\engine\\intermediate\\build\\win64\\unrealeditor\\inc\\engine\\uht\\pathfollowingagentinterface.generated.h",
            "k:\\ue_5.6\\engine\\source\\runtime\\engine\\classes\\gameframework\\movementcomponent.h",
            "k:\\ue_5.6\\engine\\intermediate\\build\\win64\\unrealeditor\\inc\\engine\\uht\\movementcomponent.generated.h",
            "k:\\ue_5.6\\engine\\intermediate\\build\\win64\\unrealeditor\\inc\\engine\\uht\\navmovementcomponent.generated.h",
            "k:\\ue_5.6\\engine\\intermediate\\build\\win64\\unrealeditor\\inc\\engine\\uht\\pawnmovementcomponent.generated.h",
            "k:\\ue_5.6\\engine\\source\\runtime\\engine\\classes\\interfaces\\networkpredictioninterface.h",
            "k:\\ue_5.6\\engine\\intermediate\\build\\win64\\unrealeditor\\inc\\engine\\uht\\networkpredictioninterface.generated.h",
            "k:\\ue_5.6\\engine\\source\\runtime\\engine\\public\\charactermovementcomponentasync.h",
            "k:\\ue_5.6\\engine\\intermediate\\build\\win64\\unrealeditor\\inc\\engine\\uht\\charactermovementcomponentasync.generated.h",
            "k:\\ue_5.6\\engine\\intermediate\\build\\win64\\unrealeditor\\inc\\engine\\uht\\charactermovementcomponent.generated.h",
            "k:\\ue_5.6\\engine\\source\\runtime\\engine\\classes\\camera\\cameracomponent.h",
            "k:\\ue_5.6\\engine\\intermediate\\build\\win64\\unrealeditor\\inc\\engine\\uht\\cameracomponent.generated.h",
            "k:\\ue_5.6\\engine\\source\\runtime\\engine\\classes\\components\\spotlightcomponent.h",
            "k:\\ue_5.6\\engine\\source\\runtime\\engine\\classes\\components\\pointlightcomponent.h",
            "k:\\ue_5.6\\engine\\source\\runtime\\engine\\classes\\components\\locallightcomponent.h",
            "k:\\ue_5.6\\engine\\source\\runtime\\engine\\classes\\components\\lightcomponent.h",
            "k:\\ue_5.6\\engine\\source\\runtime\\engine\\classes\\components\\lightcomponentbase.h",
            "k:\\ue_5.6\\engine\\intermediate\\build\\win64\\unrealeditor\\inc\\engine\\uht\\lightcomponentbase.generated.h",
            "k:\\ue_5.6\\engine\\intermediate\\build\\win64\\unrealeditor\\inc\\engine\\uht\\lightcomponent.generated.h",
            "k:\\ue_5.6\\engine\\intermediate\\build\\win64\\unrealeditor\\inc\\engine\\uht\\locallightcomponent.generated.h",
            "k:\\ue_5.6\\engine\\intermediate\\build\\win64\\unrealeditor\\inc\\engine\\uht\\pointlightcomponent.generated.h",
            "k:\\ue_5.6\\engine\\intermediate\\build\\win64\\unrealeditor\\inc\\engine\\uht\\spotlightcomponent.generated.h",
            "k:\\ue_5.6\\engine\\plugins\\enhancedinput\\source\\enhancedinput\\public\\enhancedinputcomponent.h",
            "k:\\ue_5.6\\engine\\plugins\\enhancedinput\\intermediate\\build\\win64\\unrealeditor\\inc\\enhancedinput\\uht\\enhancedinputcomponent.generated.h",
            "e:\\fpsgame\\fpsgame\\source\\fpsgame\\variant_horror\\horrorgamemode.cpp",
            "e:\\fpsgame\\fpsgame\\source\\fpsgame\\variant_horror\\horrorplayercontroller.cpp",
            "e:\\fpsgame\\fpsgame\\source\\fpsgame\\variant_horror\\horrorui.cpp",
            "e:\\fpsgame\\fpsgame\\source\\fpsgame\\variant_shooter\\ai\\envquerycontext_target.cpp",
            "k:\\ue_5.6\\engine\\source\\runtime\\aimodule\\classes\\environmentquery\\items\\envqueryitemtype_actor.h",
            "k:\\ue_5.6\\engine\\source\\runtime\\aimodule\\classes\\environmentquery\\items\\envqueryitemtype_actorbase.h",
            "k:\\ue_5.6\\engine\\source\\runtime\\aimodule\\classes\\environmentquery\\items\\envqueryitemtype_vectorbase.h",
            "k:\\ue_5.6\\engine\\source\\runtime\\aimodule\\classes\\environmentquery\\items\\envqueryitemtype.h",
            "k:\\ue_5.6\\engine\\intermediate\\build\\win64\\unrealeditor\\inc\\aimodule\\uht\\envqueryitemtype.generated.h",
            "k:\\ue_5.6\\engine\\intermediate\\build\\win64\\unrealeditor\\inc\\aimodule\\uht\\envqueryitemtype_vectorbase.generated.h",
            "k:\\ue_5.6\\engine\\intermediate\\build\\win64\\unrealeditor\\inc\\aimodule\\uht\\envqueryitemtype_actorbase.generated.h",
            "k:\\ue_5.6\\engine\\intermediate\\build\\win64\\unrealeditor\\inc\\aimodule\\uht\\envqueryitemtype_actor.generated.h",
            "k:\\ue_5.6\\engine\\source\\runtime\\aimodule\\classes\\environmentquery\\envquerytypes.h",
            "k:\\ue_5.6\\engine\\source\\runtime\\aimodule\\classes\\behaviortree\\behaviortreetypes.h",
            "k:\\ue_5.6\\engine\\source\\runtime\\aimodule\\classes\\behaviortree\\blackboard\\blackboardkey.h",
            "k:\\ue_5.6\\engine\\intermediate\\build\\win64\\unrealeditor\\inc\\aimodule\\uht\\behaviortreetypes.generated.h",
            "k:\\ue_5.6\\engine\\intermediate\\build\\win64\\unrealeditor\\inc\\aimodule\\uht\\envquerytypes.generated.h",
            "e:\\fpsgame\\fpsgame\\source\\fpsgame\\variant_shooter\\ai\\shooteraicontroller.cpp",
            "e:\\fpsgame\\fpsgame\\source\\fpsgame\\variant_shooter\\ai\\shooternpc.h",
            "e:\\fpsgame\\fpsgame\\intermediate\\build\\win64\\unrealeditor\\inc\\fpsgame\\uht\\shooternpc.generated.h",
            "k:\\ue_5.6\\engine\\plugins\\runtime\\gameplaystatetree\\source\\gameplaystatetreemodule\\public\\components\\statetreeaicomponent.h",
            "k:\\ue_5.6\\engine\\plugins\\runtime\\gameplaystatetree\\source\\gameplaystatetreemodule\\public\\components\\statetreecomponent.h",
            "k:\\ue_5.6\\engine\\source\\runtime\\aimodule\\classes\\braincomponent.h",
            "k:\\ue_5.6\\engine\\source\\runtime\\aimodule\\classes\\airesourceinterface.h",
            "k:\\ue_5.6\\engine\\intermediate\\build\\win64\\unrealeditor\\inc\\aimodule\\uht\\airesourceinterface.generated.h",
            "k:\\ue_5.6\\engine\\intermediate\\build\\win64\\unrealeditor\\inc\\aimodule\\uht\\braincomponent.generated.h",
            "k:\\ue_5.6\\engine\\plugins\\runtime\\statetree\\source\\statetreemodule\\public\\istatetreeschemaprovider.h",
            "k:\\ue_5.6\\engine\\plugins\\runtime\\statetree\\intermediate\\build\\win64\\unrealeditor\\inc\\statetreemodule\\uht\\istatetreeschemaprovider.generated.h",
            "k:\\ue_5.6\\engine\\plugins\\runtime\\statetree\\source\\statetreemodule\\public\\statetreereference.h",
            "k:\\ue_5.6\\engine\\plugins\\runtime\\statetree\\intermediate\\build\\win64\\unrealeditor\\inc\\statetreemodule\\uht\\statetreereference.generated.h",
            "k:\\ue_5.6\\engine\\plugins\\runtime\\statetree\\source\\statetreemodule\\public\\statetreeinstancedata.h",
            "k:\\ue_5.6\\engine\\source\\runtime\\coreuobject\\public\\structutils\\instancedstructcontainer.h",
            "k:\\ue_5.6\\engine\\intermediate\\build\\win64\\unrealeditor\\inc\\coreuobject\\uht\\instancedstructcontainer.generated.h",
            "k:\\ue_5.6\\engine\\plugins\\runtime\\statetree\\source\\statetreemodule\\public\\debugger\\statetreeruntimevalidation.h",
            "k:\\ue_5.6\\engine\\plugins\\runtime\\statetree\\intermediate\\build\\win64\\unrealeditor\\inc\\statetreemodule\\uht\\statetreeinstancedata.generated.h",
            "k:\\ue_5.6\\engine\\plugins\\runtime\\gameplaystatetree\\intermediate\\build\\win64\\unrealeditor\\inc\\gameplaystatetreemodule\\uht\\statetreecomponent.generated.h",
            "k:\\ue_5.6\\engine\\plugins\\runtime\\gameplaystatetree\\intermediate\\build\\win64\\unrealeditor\\inc\\gameplaystatetreemodule\\uht\\statetreeaicomponent.generated.h",
            "k:\\ue_5.6\\engine\\source\\runtime\\aimodule\\classes\\perception\\aiperceptioncomponent.h",
            "k:\\ue_5.6\\engine\\source\\runtime\\aimodule\\classes\\perception\\aisense.h",
            "k:\\ue_5.6\\engine\\intermediate\\build\\win64\\unrealeditor\\inc\\aimodule\\uht\\aisense.generated.h",
            "k:\\ue_5.6\\engine\\source\\runtime\\aimodule\\classes\\perception\\aiperceptionsystem.h",
            "k:\\ue_5.6\\engine\\source\\runtime\\aimodule\\classes\\aisubsystem.h",
            "k:\\ue_5.6\\engine\\source\\runtime\\aimodule\\classes\\aisystem.h",
            "k:\\ue_5.6\\engine\\source\\runtime\\engine\\classes\\ai\\aisystembase.h",
            "k:\\ue_5.6\\engine\\intermediate\\build\\win64\\unrealeditor\\inc\\engine\\uht\\aisystembase.generated.h",
            "k:\\ue_5.6\\engine\\intermediate\\build\\win64\\unrealeditor\\inc\\aimodule\\uht\\aisystem.generated.h",
            "k:\\ue_5.6\\engine\\intermediate\\build\\win64\\unrealeditor\\inc\\aimodule\\uht\\aisubsystem.generated.h",
            "k:\\ue_5.6\\engine\\intermediate\\build\\win64\\unrealeditor\\inc\\aimodule\\uht\\aiperceptionsystem.generated.h",
            "k:\\ue_5.6\\engine\\intermediate\\build\\win64\\unrealeditor\\inc\\aimodule\\uht\\aiperceptioncomponent.generated.h",
            "k:\\ue_5.6\\engine\\source\\runtime\\aimodule\\classes\\navigation\\pathfollowingcomponent.h",
            "k:\\ue_5.6\\engine\\source\\runtime\\navigationsystem\\public\\navigationdata.h",
            "k:\\ue_5.6\\engine\\source\\runtime\\engine\\classes\\ai\\navigation\\navigationdatainterface.h",
            "k:\\ue_5.6\\engine\\intermediate\\build\\win64\\unrealeditor\\inc\\engine\\uht\\navigationdatainterface.generated.h",
            "k:\\ue_5.6\\engine\\intermediate\\build\\win64\\unrealeditor\\inc\\navigationsystem\\uht\\navigationdata.generated.h",
            "k:\\ue_5.6\\engine\\intermediate\\build\\win64\\unrealeditor\\inc\\aimodule\\uht\\pathfollowingcomponent.generated.h",
            "e:\\fpsgame\\fpsgame\\source\\fpsgame\\variant_shooter\\ai\\shooternpc.cpp",
            "k:\\ue_5.6\\engine\\source\\runtime\\engine\\classes\\kismet\\kismetmathlibrary.h",
            "k:\\ue_5.6\\engine\\intermediate\\build\\win64\\unrealeditor\\inc\\engine\\uht\\kismetmathlibrary.generated.h",
            "k:\\ue_5.6\\engine\\source\\runtime\\engine\\classes\\kismet\\kismetmathlibrary.inl",
            "k:\\ue_5.6\\engine\\source\\runtime\\engine\\classes\\components\\capsulecomponent.h",
            "k:\\ue_5.6\\engine\\source\\runtime\\engine\\classes\\components\\shapecomponent.h",
            "k:\\ue_5.6\\engine\\intermediate\\build\\win64\\unrealeditor\\inc\\engine\\uht\\shapecomponent.generated.h",
            "k:\\ue_5.6\\engine\\intermediate\\build\\win64\\unrealeditor\\inc\\engine\\uht\\capsulecomponent.generated.h",
            "e:\\fpsgame\\fpsgame\\source\\fpsgame\\variant_shooter\\ai\\shooterstatetreeutility.cpp",
            "k:\\ue_5.6\\engine\\plugins\\runtime\\statetree\\source\\statetreemodule\\public\\statetreeexecutioncontext.h",
            "k:\\ue_5.6\\engine\\plugins\\runtime\\statetree\\source\\statetreemodule\\public\\statetree.h",
            "k:\\ue_5.6\\engine\\plugins\\runtime\\statetree\\source\\statetreemodule\\public\\statetreeschema.h",
            "k:\\ue_5.6\\engine\\plugins\\runtime\\statetree\\intermediate\\build\\win64\\unrealeditor\\inc\\statetreemodule\\uht\\statetreeschema.generated.h",
            "k:\\ue_5.6\\engine\\plugins\\runtime\\statetree\\source\\statetreemodule\\public\\statetreepropertybindings.h",
            "k:\\ue_5.6\\engine\\plugins\\runtime\\propertybindingutils\\source\\propertybindingutils\\public\\propertybindingbindablestructdescriptor.h",
            "k:\\ue_5.6\\engine\\plugins\\runtime\\propertybindingutils\\intermediate\\build\\win64\\unrealeditor\\inc\\propertybindingutils\\uht\\propertybindingbindablestructdescriptor.generated.h",
            "k:\\ue_5.6\\engine\\plugins\\runtime\\propertybindingutils\\source\\propertybindingutils\\public\\propertybindingpath.h",
            "k:\\ue_5.6\\engine\\plugins\\runtime\\propertybindingutils\\intermediate\\build\\win64\\unrealeditor\\inc\\propertybindingutils\\uht\\propertybindingpath.generated.h",
            "k:\\ue_5.6\\engine\\plugins\\runtime\\propertybindingutils\\source\\propertybindingutils\\public\\propertybindingbinding.h",
            "k:\\ue_5.6\\engine\\plugins\\runtime\\propertybindingutils\\intermediate\\build\\win64\\unrealeditor\\inc\\propertybindingutils\\uht\\propertybindingbinding.generated.h",
            "k:\\ue_5.6\\engine\\plugins\\runtime\\propertybindingutils\\source\\propertybindingutils\\public\\propertybindingbindingcollection.h",
            "k:\\ue_5.6\\engine\\plugins\\runtime\\propertybindingutils\\intermediate\\build\\win64\\unrealeditor\\inc\\propertybindingutils\\uht\\propertybindingbindingcollection.generated.h",
            "k:\\ue_5.6\\engine\\plugins\\runtime\\statetree\\source\\statetreemodule\\public\\statetreepropertyrefhelpers.h",
            "k:\\ue_5.6\\engine\\plugins\\runtime\\statetree\\intermediate\\build\\win64\\unrealeditor\\inc\\statetreemodule\\uht\\statetreepropertybindings.generated.h",
            "k:\\ue_5.6\\engine\\plugins\\runtime\\statetree\\intermediate\\build\\win64\\unrealeditor\\inc\\statetreemodule\\uht\\statetree.generated.h",
            "k:\\ue_5.6\\engine\\plugins\\runtime\\statetree\\source\\statetreemodule\\public\\statetreenoderef.h",
            "k:\\ue_5.6\\engine\\plugins\\runtime\\statetree\\source\\statetreemodule\\public\\debugger\\statetreetrace.h",
            "k:\\ue_5.6\\engine\\plugins\\runtime\\statetree\\source\\statetreemodule\\public\\statetreeasyncexecutioncontext.h",
            "e:\\fpsgame\\fpsgame\\source\\fpsgame\\variant_shooter\\shooterbulletcounterui.cpp",
            "e:\\fpsgame\\fpsgame\\source\\fpsgame\\variant_shooter\\shootercharacter.cpp",
            "e:\\fpsgame\\fpsgame\\source\\fpsgame\\variant_shooter\\shootercharacter.h",
            "e:\\fpsgame\\fpsgame\\intermediate\\build\\win64\\unrealeditor\\inc\\fpsgame\\uht\\shootercharacter.generated.h",
            "k:\\ue_5.6\\engine\\source\\runtime\\engine\\classes\\components\\pawnnoiseemittercomponent.h",
            "k:\\ue_5.6\\engine\\intermediate\\build\\win64\\unrealeditor\\inc\\engine\\uht\\pawnnoiseemittercomponent.generated.h",
            "e:\\fpsgame\\fpsgame\\source\\fpsgame\\variant_shooter\\shootergamemode.cpp",
            "k:\\ue_5.6\\engine\\source\\runtime\\engine\\classes\\kismet\\gameplaystatics.h",
            "k:\\ue_5.6\\engine\\source\\runtime\\engine\\classes\\kismet\\kismetsystemlibrary.h",
            "k:\\ue_5.6\\engine\\source\\runtime\\coreuobject\\public\\uobject\\propertyaccessutil.h",
            "k:\\ue_5.6\\engine\\intermediate\\build\\win64\\unrealeditor\\inc\\engine\\uht\\kismetsystemlibrary.generated.h",
            "k:\\ue_5.6\\engine\\source\\runtime\\engine\\classes\\sound\\dialoguetypes.h",
            "k:\\ue_5.6\\engine\\intermediate\\build\\win64\\unrealeditor\\inc\\engine\\uht\\dialoguetypes.generated.h",
            "k:\\ue_5.6\\engine\\source\\runtime\\engine\\classes\\kismet\\gameplaystaticstypes.h",
            "k:\\ue_5.6\\engine\\intermediate\\build\\win64\\unrealeditor\\inc\\engine\\uht\\gameplaystaticstypes.generated.h",
            "k:\\ue_5.6\\engine\\intermediate\\build\\win64\\unrealeditor\\inc\\engine\\uht\\gameplaystatics.generated.h",
            "e:\\fpsgame\\fpsgame\\source\\fpsgame\\variant_shooter\\shooterpickup.cpp",
            "k:\\ue_5.6\\engine\\source\\runtime\\engine\\classes\\components\\spherecomponent.h",
            "k:\\ue_5.6\\engine\\intermediate\\build\\win64\\unrealeditor\\inc\\engine\\uht\\spherecomponent.generated.h",
            "e:\\fpsgame\\fpsgame\\source\\fpsgame\\variant_shooter\\shooterplayercontroller.cpp",
            "k:\\ue_5.6\\engine\\source\\runtime\\engine\\classes\\gameframework\\playerstart.h",
            "k:\\ue_5.6\\engine\\source\\runtime\\engine\\classes\\engine\\navigationobjectbase.h",
            "k:\\ue_5.6\\engine\\intermediate\\build\\win64\\unrealeditor\\inc\\engine\\uht\\navigationobjectbase.generated.h",
            "k:\\ue_5.6\\engine\\intermediate\\build\\win64\\unrealeditor\\inc\\engine\\uht\\playerstart.generated.h",
            "e:\\fpsgame\\fpsgame\\source\\fpsgame\\variant_shooter\\shooterprojectile.cpp",
            "k:\\ue_5.6\\engine\\source\\runtime\\engine\\classes\\gameframework\\projectilemovementcomponent.h",
            "k:\\ue_5.6\\engine\\intermediate\\build\\win64\\unrealeditor\\inc\\engine\\uht\\projectilemovementcomponent.generated.h",
            "e:\\fpsgame\\fpsgame\\source\\fpsgame\\variant_shooter\\shooterui.cpp",
            "e:\\fpsgame\\fpsgame\\source\\fpsgame\\variant_shooter\\shooterweapon.cpp",
            "e:\\fpsgame\\fpsgame\\source\\fpsgame\\variant_shooter\\shooterweaponholder.cpp"
        ],
        "ImportedModules": [],
        "ImportedHeaderUnits": []
    }
}